chutes_miner_cli/cli.py
chutes_miner_cli/constants.py
chutes_miner_cli/util.py
chutes_miner_cli-0.2.4.dist-info/METADATA
chutes_miner_cli-0.2.4.dist-info/WHEEL
chutes_miner_cli-0.2.4.dist-info/entry_points.txt
chutes_miner_cli-0.2.4.dist-info/RECORD
